evnex/__init__.py
evnex/api.py
evnex/errors.py
evnex/models.py
evnex/status.py
evnex/schema/__init__.py
evnex/schema/charge_points.py
evnex/schema/commands.py
evnex/schema/cost.py
evnex/schema/org.py
evnex/schema/user.py
evnex/schema/v3/__init__.py
evnex/schema/v3/charge_points.py
evnex/schema/v3/commands.py
evnex/schema/v3/cost.py
evnex/schema/v3/generic.py
evnex/schema/v3/relationships.py
evnex-0.4.9.dist-info/METADATA
evnex-0.4.9.dist-info/WHEEL
evnex-0.4.9.dist-info/licenses/LICENSE
evnex-0.4.9.dist-info/RECORD
