Metadata-Version: 2.4
Name: evnex
Version: 0.4.9
Summary: A Python wrapper for the EVNEX Cloud API
Project-URL: repository, https://github.com/hardbyte/python-evnex
Project-URL: issues, https://github.com/hardbyte/python-evnex/issues
Author-email: Brian Thorne <brian@hardbyte.nz>
License: Apache-2.0
License-File: LICENSE
Requires-Python: >=3.11
Requires-Dist: boto3<2.0,>=1.26
Requires-Dist: httpx>=0.23
Requires-Dist: pycognito<2025,>=2023.5.0
Requires-Dist: pydantic-settings<3.0,>=2.2
Requires-Dist: pydantic<3.0.0,>2.0.0
Requires-Dist: tenacity<10.0,>=8.1
